excelform2json/__init__.py
excelform2json/excel2json/__init__.py
excelform2json/excel2json/excel2json.py
excelform2json/utils/__init__.py
excelform2json/utils/check_schema.py
excelform2json/utils/excel.py
excelform2json/utils/helpers.py
excelform2json/utils/messages.py
plugins/__init__.py
excel2jsonfile-0.3.1.dist-info/LICENSE
excel2jsonfile-0.3.1.dist-info/METADATA
excel2jsonfile-0.3.1.dist-info/WHEEL
excel2jsonfile-0.3.1.dist-info/top_level.txt
excel2jsonfile-0.3.1.dist-info/RECORD
