Metadata-Version: 2.1
Name: excel2jsonfile
Version: 0.3.1
Summary: Convert an Excel to JSON, using defined names
Home-page: https://github.com/jacbeekers/excel2jsonfile
Author: Jac. Beekers
Author-email: beekersjac@gmail.com
License: UNKNOWN
Platform: UNKNOWN
Classifier: Programming Language :: Python :: 3
Classifier: License :: OSI Approved :: MIT License
Classifier: Operating System :: OS Independent
Requires-Python: >=3.6
Requires-Dist: jsonschema
Requires-Dist: openpyxl
